week1/Task2/Addition/add.v
module add( 
input num1, num2, cin, 
output sum, cout);

reg [1:0] temp;

always@(*)
   begin
       temp = {1'b0, num1} + {1'b0, num2} + {1'b0, cin};
   end

assign sum = temp[0];
assign cout = temp[1];

endmodule

week1/Task2/Addition/add_tb.v
module add_tb();
reg num1, num2, cin;
wire sum, cout;

add uut (
.num1(num1),
.num2(num2),
.cin(cin),
.sum(sum),
.cout(cout)
);

initial begin
 $dumpfile("add.vcd");
 $dumpvars(1, add_tb);

num1 = 0; num2 = 0; cin = 0; #10;
num1 = 0; num2 = 0; cin = 1; #10;
num1 = 0; num2 = 1; cin = 0; #10;
num1 = 0; num2 = 1; cin = 1; #10;
num1 = 1; num2 = 0; cin = 0; #10;
num1 = 1; num2 = 0; cin = 1; #10;
num1 = 0; num2 = 1; cin = 0; #10;
num1 = 1; num2 = 1; cin = 1; #10;

end

endmodule

week1/Task2/Addition/add.vcd
$date
	Sat Mar  9 05:09:20 2024
$end
$version
	Icarus Verilog
$end
$timescale
	1s
$end
$scope module add_tb $end
$var wire 1 ! sum $end
$var wire 1 " cout $end
$var reg 1 # cin $end
$var reg 1 $ num1 $end
$var reg 1 % num2 $end
$upscope $end
$enddefinitions $end
#0
$dumpvars
0%
0$
0#
0"
0!
$end
#10
1!
1#
#20
0#
1%
#30
0!
1"
1#
#40
1!
0"
0#
0%
1$
#50
0!
1"
1#
#60
1!
0"
0#
1%
0$
#70
1"
1#
1$
